feffery_antd_charts/AntdArea.py
feffery_antd_charts/AntdBar.py
feffery_antd_charts/AntdBidirectionalBar.py
feffery_antd_charts/AntdBox.py
feffery_antd_charts/AntdBullet.py
feffery_antd_charts/AntdChord.py
feffery_antd_charts/AntdColumn.py
feffery_antd_charts/AntdDecompositionTree.py
feffery_antd_charts/AntdDualAxes.py
feffery_antd_charts/AntdFundFlow.py
feffery_antd_charts/AntdFunnel.py
feffery_antd_charts/AntdGauge.py
feffery_antd_charts/AntdHeatmap.py
feffery_antd_charts/AntdHistogram.py
feffery_antd_charts/AntdLine.py
feffery_antd_charts/AntdLiquid.py
feffery_antd_charts/AntdPie.py
feffery_antd_charts/AntdProgress.py
feffery_antd_charts/AntdRadar.py
feffery_antd_charts/AntdRadialBar.py
feffery_antd_charts/AntdRadialTree.py
feffery_antd_charts/AntdRingProgress.py
feffery_antd_charts/AntdRose.py
feffery_antd_charts/AntdSankey.py
feffery_antd_charts/AntdScatter.py
feffery_antd_charts/AntdStock.py
feffery_antd_charts/AntdSunburst.py
feffery_antd_charts/AntdTinyArea.py
feffery_antd_charts/AntdTinyColumn.py
feffery_antd_charts/AntdTinyLine.py
feffery_antd_charts/AntdTreemap.py
feffery_antd_charts/AntdVenn.py
feffery_antd_charts/AntdViolin.py
feffery_antd_charts/AntdWaterfall.py
feffery_antd_charts/AntdWordCloud.py
feffery_antd_charts/__init__.py
feffery_antd_charts/_imports_.py
feffery_antd_charts/alias.py
feffery_antd_charts/async-graphs.js
feffery_antd_charts/async-graphs.js.map
feffery_antd_charts/async-plots.js
feffery_antd_charts/async-plots.js.map
feffery_antd_charts/demo_data.py
feffery_antd_charts/feffery_antd_charts.min.js
feffery_antd_charts/feffery_antd_charts.min.js.map
feffery_antd_charts/metadata.json
feffery_antd_charts/package-info.json
feffery_antd_charts-0.2.3.dist-info/licenses/LICENSE
feffery_antd_charts-0.2.3.dist-info/METADATA
feffery_antd_charts-0.2.3.dist-info/WHEEL
feffery_antd_charts-0.2.3.dist-info/top_level.txt
feffery_antd_charts-0.2.3.dist-info/RECORD
